README.md
setup.cfg
setup.py
Icinga2_API/__init__.py
Icinga2_API/icinga2.py
Icinga2_API/lib/__init__.py
Icinga2_API/lib/client.py
Icinga2_API/lib/downtime.py
Icinga2_API/lib/host.py
Icinga2_API/lib/hostgroups.py
Icinga2_API/lib/notifications.py
Icinga2_API/lib/service.py
Icinga2_API/lib/servicegroups.py
Icinga2_API/lib/usergroups.py
Icinga2_API/lib/users.py
Icinga2_API/tests/Constants.py
Icinga2_API/tests/__init__.py
Icinga2_API/tests/test_hosts.py
icinga2/__init__.py
icinga2/api.py
icinga2.egg-info/PKG-INFO
icinga2.egg-info/SOURCES.txt
icinga2.egg-info/dependency_links.txt
icinga2.egg-info/top_level.txt
icinga2/lib/__init__.py
icinga2/lib/client.py
icinga2/lib/downtime.py
icinga2/lib/host.py
icinga2/lib/hostgroups.py
icinga2/lib/notifications.py
icinga2/lib/service.py
icinga2/lib/servicegroups.py
icinga2/lib/test_notification.py
icinga2/lib/usergroups.py
icinga2/lib/users.py
icinga2/tests/__init__.py
icinga2/tests/constants.py
icinga2/tests/test_hostgroups.py
icinga2/tests/test_hosts.py
icinga2/tests/test_servicegroups.py
icinga2/tests/test_services.py
icinga2/tests/test_usergroups.py