Metadata-Version: 1.0
Name: icinga2
Version: 0.5
Summary: An enhanced API to communicate with Icinga2
Home-page: https://github.com/KevinHonka/Icinga2_Python_API
Author: Kevin Honka
Author-email: kevin.honka@astosch.de
License: UNKNOWN
Keywords: Icinga2,API
Platform: UNKNOWN
